example/__init__.py
example/evaluation.py
example/example.py
example/utils_evalud.py
tratreetra/__init__.py
tratreetra/base.py
tratreetra/models.py
tratreetra/transfer.py
tratreetra/universal_tags.py
tratreetra/utils_algo.py
tratreetra-0.1.dist-info/LICENSE
tratreetra-0.1.dist-info/METADATA
tratreetra-0.1.dist-info/WHEEL
tratreetra-0.1.dist-info/top_level.txt
tratreetra-0.1.dist-info/RECORD
