Metadata-Version: 2.1
Name: tratreetra
Version: 0.1
Summary: Syntactic transfer from more resourced languages: TRAnslating TREEbanks for Syntactic TRAnsfer.
Home-page: https://github.com/alexeyev/tratreetra
Author: Anton Alekseev, Alina Tillabaeva
Author-email: anton.m.alexeyev+kyrgyz@gmail.com
Keywords: natural language processing,less-resourced languages,syntax,universal dependencies
Classifier: Programming Language :: Python :: 3.11
Classifier: License :: OSI Approved :: MIT License
Classifier: Operating System :: OS Independent
Classifier: Topic :: Text Processing :: Linguistic
Requires-Python: >=3.11
License-File: LICENSE
